fabric_utils_thelab/__init__.py
fabric_utils_thelab/mapping_function.py
fabric_utils_thelab/utils.py
fabric_utils_thelab-0.0.3.dist-info/licenses/LICENSE
fabric_utils_thelab-0.0.3.dist-info/METADATA
fabric_utils_thelab-0.0.3.dist-info/WHEEL
fabric_utils_thelab-0.0.3.dist-info/top_level.txt
fabric_utils_thelab-0.0.3.dist-info/RECORD
