Metadata-Version: 2.4
Name: fabric_utils_thelab
Version: 0.0.3
Summary: Utility functions to support Fabric ETL Pipeline
Author-email: Han Le <hle@thelabconsulting.com>
License-Expression: MIT
Project-URL: Homepage, https://github.com/TheLabConsulting/Fabric-Utils.git
Project-URL: Issues, https://github.com/TheLabConsulting/Fabric-Utils.git/Issues
Classifier: Programming Language :: Python :: 3
Classifier: Operating System :: OS Independent
Requires-Python: >=3.11
License-File: LICENSE
Dynamic: license-file
